pymodaq_plugins_oceaninsight/__init__.py
pymodaq_plugins_oceaninsight/utils.py
pymodaq_plugins_oceaninsight/daq_move_plugins/__init__.py
pymodaq_plugins_oceaninsight/daq_viewer_plugins/__init__.py
pymodaq_plugins_oceaninsight/daq_viewer_plugins/plugins_0D/__init__.py
pymodaq_plugins_oceaninsight/daq_viewer_plugins/plugins_1D/__init__.py
pymodaq_plugins_oceaninsight/daq_viewer_plugins/plugins_1D/daq_1Dviewer_Omnidriver.py
pymodaq_plugins_oceaninsight/daq_viewer_plugins/plugins_1D/daq_1Dviewer_Seabreeze.py
pymodaq_plugins_oceaninsight/daq_viewer_plugins/plugins_2D/__init__.py
pymodaq_plugins_oceaninsight/daq_viewer_plugins/plugins_ND/__init__.py
pymodaq_plugins_oceaninsight/hardware/__init__.py
pymodaq_plugins_oceaninsight/resources/VERSION
pymodaq_plugins_oceaninsight/resources/__init__.py
pymodaq_plugins_oceaninsight/resources/config_template.toml
pymodaq_plugins_oceaninsight-1.1.1.dist-info/LICENSE
pymodaq_plugins_oceaninsight-1.1.1.dist-info/METADATA
pymodaq_plugins_oceaninsight-1.1.1.dist-info/WHEEL
pymodaq_plugins_oceaninsight-1.1.1.dist-info/entry_points.txt
pymodaq_plugins_oceaninsight-1.1.1.dist-info/top_level.txt
pymodaq_plugins_oceaninsight-1.1.1.dist-info/RECORD
